gas_fsm.v
// gas_fsm.v
// Modul FSM 6-State untuk Deteksi Gas Berbahaya (VERSI DIPERBAIKI)
// Input: G,T,P,C,F,R (1 = Aman/OK, 0 = Bahaya/Gagal)
// Output: V,B,S,L,A,U (1 = ON/Aktif)
// Menggunakan 3 D-Flip-Flop (Register 3-bit)

module gas_fsm (
    // Input
    input wire clk,
    input wire rst, // Reset (active-high)
    input wire G,   // Gas (1=OK)
    input wire T,   // Suhu (1=OK)
    input wire P,   // Power (1=OK)
    input wire C,   // Arus Kipas (1=OK)
    input wire F,   // Aliran Udara (1=OK)
    input wire R,   // Reset RFID (1=Match)

    // Output
    output reg V,   // Ventilation Fan
    output reg B,   // Backup Power
    output reg S,   // Solenoid Valve
    output reg L,   // Local Alarm
    output reg A,   // Remote Alert
    output reg U    // Visual Alarm
);

    // --- Definisi State (Step 3) ---
    localparam [2:0]
        S0_STANDBY      = 3'b000,
        S1_HAZARD       = 3'b001,
        S2_FAULT_MIT    = 3'b010,
        S3_WAIT_RESET   = 3'b011,
        S4_FAILSAFE_PF  = 3'b100,
        S5_HAZARD_PF    = 3'b101;

    // --- State Register (Implementasi Step 4) ---
    reg [2:0] curr_state, next_state;
    
    // --- [FIX 1] Deklarasi Sinyal Logika Kombinatorial ---
    // (Dipindahkan dari dalam always block)
    wire isHazard = (~G) | (~T); // Gas ATAU Suhu bahaya
    wire isSafe = G & T;
    wire isPowerFail = ~P;
    wire isMitigationFault = (~C) | (~F); // Kipas ATAU Aliran gagal
    wire isResetAuth = R;


    // (Sequential Logic) - Blok D Flip-Flop
    always @(posedge clk or posedge rst) begin
        if (rst)
            curr_state <= S0_STANDBY; // Reset ke S0
        else
            curr_state <= next_state; // Update state pada detak clock
    end

    // --- Logika Transisi (Step 5) ---
    // (Combinational Logic) - Menghitung Next State
    always @(*) begin
        // Default: Tahan state saat ini
        next_state = curr_state;

        case (curr_state)
            S0_STANDBY: begin
                if (isPowerFail)
                    next_state = S4_FAILSAFE_PF;
                else if (isHazard)
                    next_state = S1_HAZARD;
            end
            
            S1_HAZARD: begin
                if (isPowerFail)
                    next_state = S5_HAZARD_PF;
                else if (isMitigationFault)
                    next_state = S2_FAULT_MIT;
                else if (isSafe)
                    next_state = S3_WAIT_RESET;
            end
            
            S2_FAULT_MIT: begin
                if (isPowerFail)
                    next_state = S5_HAZARD_PF; // Fault + Power Fail -> Hazard Power Fail
                else if (isSafe)
                    next_state = S3_WAIT_RESET;
            end
            
            S3_WAIT_RESET: begin
                if (isPowerFail)
                    next_state = S4_FAILSAFE_PF;
                else if (isResetAuth)
                    next_state = S0_STANDBY;
                else if (isHazard) // Jika gas bocor lagi sebelum direset
                    next_state = S1_HAZARD;
            end
            
            S4_FAILSAFE_PF: begin
                if (~isPowerFail) // Jika PLN Pulih (P=1)
                    next_state = S0_STANDBY;
            end
            
            S5_HAZARD_PF: begin
                if (~isPowerFail) // Jika PLN Pulih (P=1)
                    next_state = S1_HAZARD; // Kembali ke state Hazard
            end
            
            default:
                next_state = S0_STANDBY;
        endcase
    end

    // --- Logika Output (Step 7) ---
    // (Combinational Logic) - Menentukan Aktuator (Moore FSM)
    always @(*) begin
        // Default semua aktuator OFF
        V = 1'b0; B = 1'b0; S = 1'b0;
        L = 1'b0; A = 1'b0; U = 1'b0;

        case (curr_state)
            S0_STANDBY:      {V,B,S,L,A,U} = 6'b000000; // Aman
            S1_HAZARD:       {V,B,S,L,A,U} = 6'b101111; // Kipas, Valve, 3 Alarm
            S2_FAULT_MIT:    {V,B,S,L,A,U} = 6'b101111; // Sama, tapi state beda (untuk logging)
            S3_WAIT_RESET:   {V,B,S,L,A,U} = 6'b000111; // Hanya 3 Alarm (menunggu reset)
            S4_FAILSAFE_PF:  {V,B,S,L,A,U} = 6'b010000; // Hanya Backup Power
            S5_HAZARD_PF:    {V,B,S,L,A,U} = 6'b111111; // Semua ON dari UPS
            default:         {V,B,S,L,A,U} = 6'b000111; // Default ke Alarm jika state tidak diketahui
        endcase
    end

endmodule

HazardousGasLeakDetection/gas_fsm_tb.v
// gas_fsm_tb.v
// Testbench untuk FSM Deteksi Gas (VERSI DIPERBAIKI)
`timescale 1ns/1ps

module gas_fsm_tb;

    // --- Deklarasi Sinyal ---
    reg clk, rst;
    reg G, T, P, C, F, R;
    wire V, B, S, L, A, U;
    // [FIX 2] Menghapus wire [2:0] state; (tidak diperlukan untuk simulasi)

    // --- Instansiasi Modul Utama (Unit Under Test) ---
    gas_fsm UUT (
        .clk(clk), .rst(rst), .G(G), .T(T), .P(P), .C(C), .F(F), .R(R),
        .V(V), .B(B), .S(S), .L(L), .A(A), .U(U)
    );
    
    // [FIX 2] Menghapus baris 'assign state = UUT.curr_state;' 
    // (Tidak didukung oleh iverilog)

    // --- Clock Generator (Periode 10 ns) ---
    initial clk = 0;
    always #5 clk = ~clk;

    // --- Dumpfile untuk GTKWave (Membuat file .vcd) ---
    initial begin
        $dumpfile("output.vcd"); 
        $dumpvars(0, gas_fsm_tb); // Simpan semua sinyal
    end

    // --- STIMULUS (Skenario Uji) ---
    initial begin
        // Inisialisasi & Reset
        rst = 1; G=1; T=1; P=1; C=1; F=1; R=0;
        #20; // Tunggu 20 ns
        rst = 0; // Lepas reset
        $display("Time=%0t: S0 (Standby)", $time);

        // --- Skenario 1: Gas Bocor (Pindah ke S1) ---
        #100;
        G = 0; // Gas Bocor!
        #10;
        $display("Time=%0t: S1 (Hazard) - Gas Bocor", $time);

        // --- Skenario 2: Kipas Gagal (Pindah ke S2) ---
        #100;
        C = 0; // Arus Kipas Mati!
        #10;
        $display("Time=%0t: S2 (Fault) - Kipas Rusak", $time);

        // --- Skenario 3: PLN Mati (Pindah ke S5) ---
        #100;
        P = 0; // PLN Mati!
        #10;
        $display("Time=%0t: S5 (Hazard Power Fail)", $time);
        
        // --- Skenario 4: PLN Pulih (Kembali ke S2) ---
        #100;
        P = 1; // PLN Pulih
        #10;
        $display("Time=%0t: S2 (Fault) - PLN Pulih", $time);

        // --- Skenario 5: Bahaya Selesai (Pindah ke S3) ---
        #100;
        G = 1; // Gas Aman
        C = 1; // Kipas (dimisalkan) sudah OK
        #10;
        $display("Time=%0t: S3 (Waiting for Reset)", $time);

        // --- Skenario 6: Otorisasi Reset (Pindah ke S0) ---
        #100;
        R = 1; // Otorisasi RFID
        #10;
        R = 0; // Lepas kartu
        #10;
        $display("Time=%0t: S0 (Standby) - Sistem Reset", $time);

        // --- Skenario 7: PLN Mati saat Standby (Pindah ke S4) ---
        #100;
        P = 0; // PLN Mati
        #10;
        $display("Time=%0t: S4 (Failsafe Power Fail)", $time);

        // --- Skenario 8: PLN Pulih (Kembali ke S0) ---
        #100;
        P = 1; // PLN Pulih
        #10;
        $display("Time=%0t: S0 (Standby) - PLN Pulih", $time);

        // Akhiri simulasi
        #50;
        $display("Simulasi selesai pada waktu %0t ns", $time);
        $finish;
    end

endmodule

output.vcd
$date
	Mon Dec 01 21:45:44 2025
$end
$version
	Icarus Verilog
$end
$timescale
	1ps
$end
$scope module gas_fsm_tb $end
$var wire 1 ! V $end
$var wire 1 " U $end
$var wire 1 # S $end
$var wire 1 $ L $end
$var wire 1 % B $end
$var wire 1 & A $end
$var reg 1 ' C $end
$var reg 1 ( F $end
$var reg 1 ) G $end
$var reg 1 * P $end
$var reg 1 + R $end
$var reg 1 , T $end
$var reg 1 - clk $end
$var reg 1 . rst $end
$scope module UUT $end
$var wire 1 ' C $end
$var wire 1 ( F $end
$var wire 1 ) G $end
$var wire 1 * P $end
$var wire 1 + R $end
$var wire 1 , T $end
$var wire 1 - clk $end
$var wire 1 / isHazard $end
$var wire 1 0 isMitigationFault $end
$var wire 1 1 isPowerFail $end
$var wire 1 2 isResetAuth $end
$var wire 1 3 isSafe $end
$var wire 1 . rst $end
$var parameter 3 4 S0_STANDBY $end
$var parameter 3 5 S1_HAZARD $end
$var parameter 3 6 S2_FAULT_MIT $end
$var parameter 3 7 S3_WAIT_RESET $end
$var parameter 3 8 S4_FAILSAFE_PF $end
$var parameter 3 9 S5_HAZARD_PF $end
$var reg 1 & A $end
$var reg 1 % B $end
$var reg 1 $ L $end
$var reg 1 # S $end
$var reg 1 " U $end
$var reg 1 ! V $end
$var reg 3 : curr_state [2:0] $end
$var reg 3 ; next_state [2:0] $end
$upscope $end
$upscope $end
$enddefinitions $end
$comment Show the parameter values. $end
$dumpall
b101 9
b100 8
b11 7
b10 6
b1 5
b0 4
$end
#0
$dumpvars
b0 ;
b0 :
13
02
01
00
0/
1.
0-
1,
0+
1*
1)
1(
1'
0&
0%
0$
0#
0"
0!
$end
#5000
1-
#10000
0-
#15000
1-
#20000
0-
0.
#25000
1-
#30000
0-
#35000
1-
#40000
0-
#45000
1-
#50000
0-
#55000
1-
#60000
0-
#65000
1-
#70000
0-
#75000
1-
#80000
0-
#85000
1-
#90000
0-
#95000
1-
#100000
0-
#105000
1-
#110000
0-
#115000
1-
#120000
b1 ;
1/
03
0-
0)
#125000
1!
1#
1$
1&
1"
b1 :
1-
#130000
0-
#135000
1-
#140000
0-
#145000
1-
#150000
0-
#155000
1-
#160000
0-
#165000
1-
#170000
0-
#175000
1-
#180000
0-
#185000
1-
#190000
0-
#195000
1-
#200000
0-
#205000
1-
#210000
0-
#215000
1-
#220000
0-
#225000
1-
#230000
b10 ;
10
0-
0'
#235000
1"
1&
1$
1#
1!
b10 :
1-
#240000
0-
#245000
1-
#250000
0-
#255000
1-
#260000
0-
#265000
1-
#270000
0-
#275000
1-
#280000
0-
#285000
1-
#290000
0-
#295000
1-
#300000
0-
#305000
1-
#310000
0-
#315000
1-
#320000
0-
#325000
1-
#330000
0-
#335000
1-
#340000
b101 ;
11
0-
0*
#345000
1%
1"
1&
1$
1#
1!
b101 :
1-
#350000
0-
#355000
1-
#360000
0-
#365000
1-
#370000
0-
#375000
1-
#380000
0-
#385000
1-
#390000
0-
#395000
1-
#400000
0-
#405000
1-
#410000
0-
#415000
1-
#420000
0-
#425000
1-
#430000
0-
#435000
1-
#440000
0-
#445000
1-
#450000
b1 ;
01
0-
1*
#455000
1"
1&
1$
1#
0%
1!
b10 ;
b1 :
1-
#460000
0-
#465000
1"
1&
1$
1#
1!
b10 :
1-
#470000
0-
#475000
1-
#480000
0-
#485000
1-
#490000
0-
#495000
1-
#500000
0-
#505000
1-
#510000
0-
#515000
1-
#520000
0-
#525000
1-
#530000
0-
#535000
1-
#540000
0-
#545000
1-
#550000
0-
#555000
1-
#560000
00
0/
b11 ;
13
0-
1'
1)
#565000
1"
1&
1$
0#
0!
b11 :
1-
#570000
0-
#575000
1-
#580000
0-
#585000
1-
#590000
0-
#595000
1-
#600000
0-
#605000
1-
#610000
0-
#615000
1-
#620000
0-
#625000
1-
#630000
0-
#635000
1-
#640000
0-
#645000
1-
#650000
0-
#655000
1-
#660000
0-
#665000
1-
#670000
b0 ;
0-
12
1+
#675000
0"
0&
0$
b0 :
1-
#680000
0-
02
0+
#685000
1-
#690000
0-
#695000
1-
#700000
0-
#705000
1-
#710000
0-
#715000
1-
#720000
0-
#725000
1-
#730000
0-
#735000
1-
#740000
0-
#745000
1-
#750000
0-
#755000
1-
#760000
0-
#765000
1-
#770000
0-
#775000
1-
#780000
0-
#785000
1-
#790000
b100 ;
11
0-
0*
#795000
1%
b100 :
1-
#800000
0-
#805000
1-
#810000
0-
#815000
1-
#820000
0-
#825000
1-
#830000
0-
#835000
1-
#840000
0-
#845000
1-
#850000
0-
#855000
1-
#860000
0-
#865000
1-
#870000
0-
#875000
1-
#880000
0-
#885000
1-
#890000
0-
#895000
1-
#900000
b0 ;
01
0-
1*
#905000
0%
b0 :
1-
